panstat/__init__.py
panstat/banner.txt
panstat/version.json
panstat/bin/__init__.py
panstat/bin/_batch.py
panstat/bin/_merge.py
panstat/bin/_plot.py
panstat/bin/_stat.py
panstat/bin/main.py
panstat/plot/__init__.py
panstat/plot/boxplot_tpl.py
panstat/plot/pointplot_tpl.py
panstat/plot/process_data.py
panstat/stat/__init__.py
panstat/util/__init__.py
panstat/util/merge.py
panstat/util/shell.py
panstat-1.0.4.dist-info/METADATA
panstat-1.0.4.dist-info/WHEEL
panstat-1.0.4.dist-info/entry_points.txt
panstat-1.0.4.dist-info/top_level.txt
panstat-1.0.4.dist-info/RECORD
