Metadata-Version: 2.1
Name: panstat
Version: 1.0.4
Summary: A Python toolkit for the statistical and visualization of core and pan genes in Pan-genome
Home-page: https://github.com/suqingdong/panstat
Author: suqingdong
Author-email: suqingdong1114@gmail.com
License: MIT License
Platform: UNKNOWN
Classifier: Development Status :: 5 - Production/Stable
Classifier: Operating System :: OS Independent
Classifier: Intended Audience :: Developers
Classifier: License :: OSI Approved :: MIT License
Classifier: Programming Language :: Python
Classifier: Programming Language :: Python :: 3
Classifier: Programming Language :: Python :: 3.9
Classifier: Programming Language :: Python :: 3.10
Classifier: Programming Language :: Python :: 3.11
Classifier: Topic :: Software Development :: Libraries
Requires-Dist: click (>=8.1.3)
Requires-Dist: pandas (>=1.5.3)
Requires-Dist: tqdm (>=4.65.0)
Requires-Dist: simple-loggers (>=1.0.5)
Requires-Dist: makejob (>=1.0.1)
